sold/__init__.py
sold/allocate.py
sold/auction.py
sold/bid.py
sold/pay.py
sold-0.0.4.dist-info/LICENSE
sold-0.0.4.dist-info/WHEEL
sold-0.0.4.dist-info/METADATA
sold-0.0.4.dist-info/RECORD
