Metadata-Version: 2.1
Name: sold
Version: 0.0.4
Summary: A library for the study of auctions.
Author: Vincent Knight
Author-email: knightva@cardiff.ac.uk
Requires-Python: >=3.11
Classifier: License :: OSI Approved :: MIT License
Requires-Dist: numpy >= 1.26.1
Requires-Dist: scipy >= 1.14.1
Requires-Dist: sphinx ; extra == "doc"
Requires-Dist: sphinx-rtd-theme ; extra == "doc"
Requires-Dist: sphinx-togglebutton ; extra == "doc"
Provides-Extra: doc
